dodoo_loader/__init__.py
dodoo_loader/cli.py
dodoo_loader-0.6.5.dist-info/LICENSE
dodoo_loader-0.6.5.dist-info/METADATA
dodoo_loader-0.6.5.dist-info/WHEEL
dodoo_loader-0.6.5.dist-info/entry_points.txt
dodoo_loader-0.6.5.dist-info/top_level.txt
dodoo_loader-0.6.5.dist-info/RECORD
