Metadata-Version: 2.1
Name: dodoo-loader
Version: 0.6.5
Summary: dodoo load subcommand
Home-page: http://github.com/xoe-labs/dodoo-loader
Author: XOE Labs
Author-email: info@xoe.solutions
License: LGPLv3+
Platform: UNKNOWN
Classifier: Development Status :: 4 - Beta
Classifier: Intended Audience :: Developers
Classifier: License :: OSI Approved :: GNU Lesser General Public License v3 or later (LGPLv3+)
Classifier: Programming Language :: Python :: 2.7
Classifier: Programming Language :: Python :: 3.5
Classifier: Programming Language :: Python :: 3.6
Classifier: Programming Language :: Python :: 3.7
Classifier: Framework :: Odoo
Requires-Dist: dodoo (>=2.0.0.rc6)
Requires-Dist: networkx
Requires-Dist: pandas
Requires-Dist: xlrd
Requires-Dist: future
Requires-Dist: pyyaml (==3.12) ; python_version < "3.7"
Requires-Dist: pyyaml (==3.13) ; python_version >= "3.7"
